switch_audio_device/__init__.py
switch_audio_device/main.py
switch_audio_device-0.1.5.dist-info/LICENSE
switch_audio_device-0.1.5.dist-info/METADATA
switch_audio_device-0.1.5.dist-info/WHEEL
switch_audio_device-0.1.5.dist-info/entry_points.txt
switch_audio_device-0.1.5.dist-info/top_level.txt
switch_audio_device-0.1.5.dist-info/RECORD
