Metadata-Version: 2.1
Name: switch_audio_device
Version: 0.1.5
Project-URL: Source, https://gitlab.com/sandeep-datta/switch_audio_device
Project-URL: Tracker, https://gitlab.com/sandeep-datta/switch_audio_device/issues
Classifier: Programming Language :: Python :: 3
Classifier: License :: OSI Approved :: MIT License
Classifier: Operating System :: POSIX :: Linux
Requires-Python: >=3.6
License-File: LICENSE
Requires-Dist: pulsectl
